ToDo.py
Simple_ToDo_List-0.0.1.dist-info/METADATA
Simple_ToDo_List-0.0.1.dist-info/WHEEL
Simple_ToDo_List-0.0.1.dist-info/entry_points.txt
Simple_ToDo_List-0.0.1.dist-info/top_level.txt
Simple_ToDo_List-0.0.1.dist-info/RECORD
